{
"type": "FeatureCollection",
"name": "malamhari_2020",
"crs": { "type": "name", "properties": { "name": "urn:ogc:def:crs:OGC:1.3:CRS84" } },
"features": [
{ "type": "Feature", "properties": { "No": 1, "Jenis_krim": "Pencurian kendaraan bermotor roda 2", "lokasi": "Perum Puri cikarang hijau Ds. Karang asih Kec.Cikarang Utara", "X": 107.1564913, "Y": -6.2512364 }, "geometry": { "type": "Point", "coordinates": [ 107.1564913, -6.2512364 ] } },
{ "type": "Feature", "properties": { "No": 2, "Jenis_krim": "Pencurian berat", "lokasi": "Kotrkan Bapak Mada Kp cibarengkok RT 001\/002 Ds Kel jatiwangi Kec Cikarang", "X": 107.0862596, "Y": -6.3219422 }, "geometry": { "type": "Point", "coordinates": [ 107.0862596, -6.3219422 ] } },
{ "type": "Feature", "properties": { "No": 3, "Jenis_krim": "Pencurian", "lokasi": "ATM Bank Mandiri Pom Bensin Warung Bongkok Ds.Telaga Murni Kec.Cikarang Barat", "X": 107.1175469, "Y": -6.2696556 }, "geometry": { "type": "Point", "coordinates": [ 107.1175469, -6.2696556 ] } },
{ "type": "Feature", "properties": { "No": 4, "Jenis_krim": "Pencurian berat", "lokasi": "PT.LINFOX LOGISTICS INDONESIA Jl.Irian Blok.S No.7A KWS.MM2100 Ds.Cikedokan Kec.Cikarang Barat", "X": 107.0974533, "Y": -6.3295035 }, "geometry": { "type": "Point", "coordinates": [ 107.0974533, -6.3295035 ] } },
{ "type": "Feature", "properties": { "No": 5, "Jenis_krim": "Pencurian berat", "lokasi": "Kp. Leuweung malang Rt. 001\/03 Desa Sukaresmi Kec. Cikarang Selatan", "X": 107.1205918, "Y": -6.3327198 }, "geometry": { "type": "Point", "coordinates": [ 107.1205918, -6.3327198 ] } },
{ "type": "Feature", "properties": { "No": 6, "Jenis_krim": "Pencurian kendaraan bermotor roda 2", "lokasi": "Jl Trias Kp. Sasak tiga Rt 02\/04 Kec. Tambun Selatan", "X": 107.075707, "Y": -6.2514584 }, "geometry": { "type": "Point", "coordinates": [ 107.075707, -6.2514584 ] } },
{ "type": "Feature", "properties": { "No": 7, "Jenis_krim": "Pencurian kendaraan bermotor roda 4", "lokasi": "Perum Jatimulya Jl. Nusantara VII No. 24\/ Blok A Rt 02\/15 Kel. Jatimulya Kec. Tambun Selatan", "X": 107.050011, "Y": -6.258775 }, "geometry": { "type": "Point", "coordinates": [ 107.050011, -6.258775 ] } },
{ "type": "Feature", "properties": { "No": 8, "Jenis_krim": "Pencurian kendaraan bermotor roda 2", "lokasi": "Di Rumah Makan Sandi Minang Kp.Gardu Sawah Rt 002\/001 Ds.Kalijaya Kec.Cikarang Barat", "X": 107.1155476, "Y": -6.27211 }, "geometry": { "type": "Point", "coordinates": [ 107.1155476, -6.27211 ] } },
{ "type": "Feature", "properties": { "No": 9, "Jenis_krim": "Pencurian", "lokasi": "JL  CEMARA BLOK F NO 297 RT 08\/13 KEL JATIMULYA KEC TAMBUN SELATAN", "X": 107021357.0, "Y": -6.268435 }, "geometry": { "type": "Point", "coordinates": [ 107021357.0, -6.268435 ] } },
{ "type": "Feature", "properties": { "No": 10, "Jenis_krim": "Pencurian berat", "lokasi": "Di lapak Pisang ‘’PUTRA MANDIRI’’ Blok A Pasar Induk Cibitung Kel.Wanasari Kec.Cibitung", "X": 107.0793746, "Y": -6.2658618 }, "geometry": { "type": "Point", "coordinates": [ 107.0793746, -6.2658618 ] } },
{ "type": "Feature", "properties": { "No": 11, "Jenis_krim": "Pencurian berat", "lokasi": "PT.HARAPAN SUKSES JAYA Kp.Jaya Raga Rt 05\/07 Ds.Sukadanau Kec.cikarang Barat", "X": 107.1177314, "Y": -6.2739433 }, "geometry": { "type": "Point", "coordinates": [ 107.1177314, -6.2739433 ] } },
{ "type": "Feature", "properties": { "No": 12, "Jenis_krim": "Penganiayaan berat", "lokasi": "Kp. Pulo Kapuk Rt 01\/06 Ds. Mekar mukti Kec. Cikarang Utara", "X": 107.1552315, "Y": -6.2924895 }, "geometry": { "type": "Point", "coordinates": [ 107.1552315, -6.2924895 ] } },
{ "type": "Feature", "properties": { "No": 13, "Jenis_krim": "Pencurian berat", "lokasi": "Perum. WahanaCikarang Blok A.6 No. 4 Rt. 006 \/ 009 DesaSukadamiKec. Cikarang Selatan", "X": 107.1064558, "Y": -6.3590143 }, "geometry": { "type": "Point", "coordinates": [ 107.1064558, -6.3590143 ] } },
{ "type": "Feature", "properties": { "No": 14, "Jenis_krim": "Pencurian kendaraan bermotor roda 2", "lokasi": "parkiran Masjid AL-HIKMAH : Villa Mutiara Jaya III Blok M Rt 002\/010 Ds.Wanajaya Kec.Cibitung", "X": 107.0970166, "Y": -6.2540895 }, "geometry": { "type": "Point", "coordinates": [ 107.0970166, -6.2540895 ] } },
{ "type": "Feature", "properties": { "No": 15, "Jenis_krim": "Pencurian kekerasan", "lokasi": "Jalan Raya CBL Kp. Gabus Tengah Dusun 2 Rt 003\/003 Ds. Srijaya Kec. Tambun Utara", "X": 107.0783218, "Y": -6.1944588 }, "geometry": { "type": "Point", "coordinates": [ 107.0783218, -6.1944588 ] } },
{ "type": "Feature", "properties": { "No": 16, "Jenis_krim": "Pencurian kendaraan bermotor roda 2", "lokasi": "KP.Cibitung Babakan Rt 004\/002 Kel.Telagaasih Kec.Cikarang Barat", "X": 107.1011837, "Y": -6.2679337 }, "geometry": { "type": "Point", "coordinates": [ 107.1011837, -6.2679337 ] } }
]
}
